I2MC/I2MC.py
I2MC/__init__.py
I2MC/version.py
I2MC/plot/__init__.py
I2MC/plot/plot.py
i2mc-2.2.7.dist-info/licenses/LICENSE
i2mc-2.2.7.dist-info/METADATA
i2mc-2.2.7.dist-info/WHEEL
i2mc-2.2.7.dist-info/top_level.txt
i2mc-2.2.7.dist-info/RECORD
