Metadata-Version: 2.4
Name: I2MC
Version: 2.2.7
Summary: Noise-robust fixation classification (I2MC).
Home-page: https://github.com/dcnieho/I2MC_Python
Author: Diederick Niehorster
Author-email: diederick_c.niehorster@humlab.lu.se
License: MIT License
Project-URL: Source Code, https://github.com/dcnieho/I2MC_Python
Classifier: Programming Language :: Python :: 3
Classifier: License :: OSI Approved :: MIT License
Classifier: Operating System :: OS Independent
Requires-Python: >=3.6
License-File: LICENSE
Requires-Dist: numpy
Requires-Dist: matplotlib
Requires-Dist: scipy
Requires-Dist: pandas
Dynamic: author
Dynamic: author-email
Dynamic: classifier
Dynamic: description
Dynamic: description-content-type
Dynamic: home-page
Dynamic: license
Dynamic: license-file
Dynamic: project-url
Dynamic: requires-dist
Dynamic: requires-python
Dynamic: summary
